{
  "analytics_identifier": null,
  "base_path": "/find-a-visa-application-centre",
  "content_id": "aa055bd6-fde1-4471-8ac2-ac86241b4898",
  "description": "Find the address, contact details and opening times of the UK visa application centre for your country.",
  "details": {
    "body": "<p>Find the opening times, address and contact details for UK visa application centres near you.</p>\n\n<p><a href=\"https://www.gov.uk/contact-ukvi-outside-uk\">Contact the international enquiry service</a> if you have questions about applications made from outside the UK.</p>\n\n<p>You can check for the latest <a href=\"/news-and-communications?keywords=visa&amp;level_one_taxon=&amp;organisations%5B%5D=uk-visas-and-immigration&amp;public_timestamp%5Bfrom%5D=&amp;public_timestamp%5Bto%5D=&amp;order=updated-newest\">changes to visa applications.</a></p>\n\n<div role=\"note\" aria-label=\"Information\" class=\"application-notice info-notice\">\n<p>If you need to attend an appointment, you must complete your application online first.</p>\n</div>\n\n<h2 id=\"a\">A</h2>\n\n<p>Afghanistan - apply at your nearest accessible visa application centre</p>\n\n<p><a rel=\"external\" href=\"https://uk.tlscontact.com/al/tia/splash.php\">Albania</a></p>\n\n<p><a rel=\"external\" href=\"https://uk.tlscontact.com/dz/alg/splash.php\">Algeria</a></p>\n\n<p>Andorra - apply through <a rel=\"external\" href=\"https://uk.tlscontact.com/es/mad/splash.php\">Spain</a></p>\n\n<p><a rel=\"external\" href=\"https://uk.tlscontact.com/ao/lad/splash.php\">Angola</a></p>\n\n<p>Anguilla - apply through <a rel=\"external\" href=\"https://visa.vfsglobal.com/brb/en/gbr/attend-centre\">Barbados</a></p>\n\n<p>Antigua and Barbuda - apply through <a rel=\"external\" href=\"https://visa.vfsglobal.com/brb/en/gbr/attend-centre\">Barbados</a></p>\n\n<p><a rel=\"external\" href=\"https://visa.vfsglobal.com/arg/en/gbr/attend-centre\">Argentina</a></p>\n\n<p><a rel=\"external\" href=\"https://uk.tlscontact.com/am/evn/splash.php\">Armenia</a></p>\n\n<p>Aruba - apply through <a rel=\"external\" href=\"https://visa.vfsglobal.com/ven/en/gbr/attend-centre\">Venezuela</a></p>\n\n<p>Ascension - apply through <a href=\"/government/publications/st-helena-apply-for-a-uk-visa\">St. Helena</a></p>\n\n<p><a rel=\"external\" href=\"https://visa.vfsglobal.com/aus/en/gbr/attend-centre\">Australia</a></p>\n\n<p><a rel=\"external\" href=\"https://uk.tlscontact.com/at/vie/splash.php\">Austria</a></p>\n\n<p><a rel=\"external\" href=\"https://uk.tlscontact.com/az/gyd/splash.php\">Azerbaijan</a></p>\n\n<h2 id=\"b\">B</h2>\n\n<p><a rel=\"external\" href=\"https://visa.vfsglobal.com/bhs/en/gbr/attend-centre\">Bahamas</a></p>\n\n<p><a rel=\"external\" href=\"https://visa.vfsglobal.com/bhr/en/gbr/attend-centre\">Bahrain</a></p>\n\n<p><a rel=\"external\" href=\"https://visa.vfsglobal.com/bgd/en/gbr/attend-centre\">Bangladesh</a></p>\n\n<p><a rel=\"external\" href=\"https://visa.vfsglobal.com/brb/en/gbr/attend-centre\">Barbados</a></p>\n\n<p><a rel=\"external\" href=\"https://uk.tlscontact.com/by/msq/splash.php\">Belarus</a></p>\n\n<p><a rel=\"external\" href=\"https://uk.tlscontact.com/be/bru/splash.php\">Belgium</a></p>\n\n<p>Belize - apply at your nearest accessible visa application centre in the Americas</p>\n\n<p>Benin - apply through <a rel=\"external\" href=\"https://uk.tlscontact.com/ng/abv/splash.php\">Nigeria</a></p>\n\n<p><a rel=\"external\" href=\"https://visa.vfsglobal.com/bmu/en/gbr/attend-centre\">Bermuda</a></p>\n\n<p><a rel=\"external\" href=\"https://visa.vfsglobal.com/btn/en/gbr/attend-centre\">Bhutan</a></p>\n\n<p><a rel=\"external\" href=\"https://visa.vfsglobal.com/bol/en/gbr/attend-centre\">Bolivia</a></p>\n\n<p>Bonaire - apply through <a rel=\"external\" href=\"https://visa.vfsglobal.com/ven/en/gbr/attend-centre\">Venezuela</a></p>\n\n<p><a rel=\"external\" href=\"https://uk.tlscontact.com/ba/sjj/splash.php\">Bosnia and Herzegovina</a></p>\n\n<p><a rel=\"external\" href=\"https://uk.tlscontact.com/bw/gbe/splash.php\">Botswana</a></p>\n\n<p><a rel=\"external\" href=\"https://visa.vfsglobal.com/bra/en/gbr/attend-centre\">Brazil</a></p>\n\n<p>British Virgin Islands - apply through <a rel=\"external\" href=\"https://visa.vfsglobal.com/brb/en/gbr/attend-centre\">Barbados</a></p>\n\n<p><a rel=\"external\" href=\"https://visa.vfsglobal.com/brn/en/gbr/attend-centre\">Brunei</a></p>\n\n<p><a rel=\"external\" href=\"https://uk.tlscontact.com/bg/sof/splash.php\">Bulgaria</a></p>\n\n<p>Burkina Faso - apply through <a rel=\"external\" href=\"https://uk.tlscontact.com/gh/acc/splash.php\">Ghana</a></p>\n\n<p>Burundi - apply through <a rel=\"external\" href=\"https://uk.tlscontact.com/rw/kgl/splash.php\">Rwanda</a></p>\n\n<h2 id=\"c\">C</h2>\n\n<p><a rel=\"external\" href=\"https://visa.vfsglobal.com/khm/en/gbr/attend-centre\">Cambodia</a></p>\n\n<p><a rel=\"external\" href=\"https://uk.tlscontact.com/cm/yao/splash.php\">Cameroon</a></p>\n\n<p><a rel=\"external\" href=\"https://visa.vfsglobal.com/can/en/gbr/attend-centre\">Canada</a></p>\n\n<p>Cape Verde - apply through <a rel=\"external\" href=\"https://uk.tlscontact.com/sn/dkr/splash.php\">Senegal</a></p>\n\n<p><a rel=\"external\" href=\"https://visa.vfsglobal.com/cym/en/gbr/attend-centre\">Cayman Islands</a></p>\n\n<p>Central African Republic - apply through <a rel=\"external\" href=\"https://uk.tlscontact.com/cm/yao/splash.php\">Cameroon</a></p>\n\n<p>Chad - apply through <a rel=\"external\" href=\"https://uk.tlscontact.com/cm/yao/splash.php\">Cameroon</a></p>\n\n<p><a rel=\"external\" href=\"https://visa.vfsglobal.com/chl/en/gbr/attend-centre\">Chile</a></p>\n\n<p><a rel=\"external\" href=\"https://visa.vfsglobal.com/chn/en/gbr/attend-centre\">China</a></p>\n\n<p><a rel=\"external\" href=\"https://visa.vfsglobal.com/col/en/gbr/attend-centre\">Colombia</a></p>\n\n<p>Comoros - apply through <a rel=\"external\" href=\"https://uk.tlscontact.com/mu/mru/splash.php\">Mauritius</a></p>\n\n<p>Congo - apply through <a rel=\"external\" href=\"https://uk.tlscontact.com/cd/fih/splash.php\">Democratic Republic of the Congo</a></p>\n\n<p>Costa Rica - apply at your nearest accessible visa application centre in the Americas</p>\n\n<p><a rel=\"external\" href=\"https://uk.tlscontact.com/hr/zag/splash.php\">Croatia</a></p>\n\n<p><a href=\"/government/publications/cuba-apply-for-a-uk-visa\">Cuba</a></p>\n\n<p>Curaçao - apply through <a rel=\"external\" href=\"https://visa.vfsglobal.com/ven/en/gbr/attend-centre\">Venezuela</a></p>\n\n<p><a rel=\"external\" href=\"https://uk.tlscontact.com/cy/ecn/page.php?pid=center_info\">Cyprus (North)</a></p>\n\n<p><a rel=\"external\" href=\"https://uk.tlscontact.com/cy/nic/page.php?pid=center_info\">Cyprus (South)</a></p>\n\n<p><a rel=\"external\" href=\"https://uk.tlscontact.com/cz/prg/splash.php\">Czech Republic</a></p>\n\n<h2 id=\"d\">D</h2>\n\n<p><a rel=\"external\" href=\"https://uk.tlscontact.com/cd/fih/splash.php\">Democratic Republic of the Congo</a></p>\n\n<p><a rel=\"external\" href=\"https://uk.tlscontact.com/dk/cph/splash.php\">Denmark</a></p>\n\n<p>Djibouti - apply through <a rel=\"external\" href=\"https://uk.tlscontact.com/et/add/splash.php\">Ethiopia</a></p>\n\n<p><a rel=\"external\" href=\"https://visa.vfsglobal.com/dma/en/gbr/attend-centre\">Dominica</a></p>\n\n<p><a rel=\"external\" href=\"https://visa.vfsglobal.com/dom/en/gbr/attend-centre\">Dominican Republic</a></p>\n\n<h2 id=\"e\">E</h2>\n\n<p>East Timor - apply through <a rel=\"external\" href=\"https://visa.vfsglobal.com/idn/en/gbr/attend-centre\">Indonesia</a></p>\n\n<p><a rel=\"external\" href=\"https://visa.vfsglobal.com/ecu/en/gbr/attend-centre\">Ecuador</a></p>\n\n<p><a rel=\"external\" href=\"https://uk.tlscontact.com/eg/aly/splash.php\">Egypt</a></p>\n\n<p><a rel=\"external\" href=\"https://visa.vfsglobal.com/slv/en/gbr/attend-centre\">El Salvador</a></p>\n\n<p>Equatorial Guinea - apply at your nearest accessible visa application centre in West Africa</p>\n\n<p>Eritrea - apply through <a rel=\"external\" href=\"https://uk.tlscontact.com/ke/mba/splash.php\">Kenya</a></p>\n\n<p><a rel=\"external\" href=\"https://uk.tlscontact.com/ee/tll/splash.php\">Estonia</a></p>\n\n<p>Eswatini - apply through <a rel=\"external\" href=\"https://uk.tlscontact.com/za/cpt/splash.php\">South Africa</a></p>\n\n<p><a rel=\"external\" href=\"https://uk.tlscontact.com/et/add/splash.php\">Ethiopia</a></p>\n\n<h2 id=\"f\">F</h2>\n\n<p><a href=\"/government/publications/falkland-islands-apply-for-a-uk-visa\">Falkland Islands</a></p>\n\n<p>The Faroes - apply through <a rel=\"external\" href=\"https://uk.tlscontact.com/dk/cph/splash.php\">Denmark</a></p>\n\n<p><a rel=\"external\" href=\"https://visa.vfsglobal.com/fji/en/gbr/attend-centre\">Fiji</a></p>\n\n<p><a rel=\"external\" href=\"https://uk.tlscontact.com/fi/hel/splash.php\">Finland</a></p>\n\n<p><a rel=\"external\" href=\"https://uk.tlscontact.com/fr/par/splash.php\">France</a></p>\n\n<p>French Guiana - apply through <a rel=\"external\" href=\"https://visa.vfsglobal.com/guy/en/gbr/attend-centre\">Guyana</a></p>\n\n<h2 id=\"g\">G</h2>\n\n<p><a rel=\"external\" href=\"https://pos.tlscontact.com/\">Gabon</a></p>\n\n<p><a rel=\"external\" href=\"https://uk.tlscontact.com/gm/bjl/splash.php\">Gambia</a></p>\n\n<p><a rel=\"external\" href=\"https://uk.tlscontact.com/ge/tbs/splash.php\">Georgia</a></p>\n\n<p><a rel=\"external\" href=\"https://uk.tlscontact.com/de/DUS/splash.php\">Germany</a></p>\n\n<p><a rel=\"external\" href=\"https://uk.tlscontact.com/gh/acc/splash.php\">Ghana</a></p>\n\n<p><a href=\"/government/publications/gibraltar-apply-for-a-uk-visa/apply-for-a-uk-visa-in-gibraltar\">Gibraltar</a></p>\n\n<p><a rel=\"external\" href=\"https://uk.tlscontact.com/gr/ath/splash.php\">Greece</a></p>\n\n<p>Greenland - apply through <a rel=\"external\" href=\"https://uk.tlscontact.com/dk/cph/splash.php\">Denmark</a></p>\n\n<p>Grenada - apply through <a rel=\"external\" href=\"https://visa.vfsglobal.com/brb/en/gbr/attend-centre\">Barbados</a></p>\n\n<p>Guatemala - apply at your nearest accessible visa application centre in the Americas</p>\n\n<p>Guinea - apply through <a rel=\"external\" href=\"https://uk.tlscontact.com/sl/fna/splash.php\">Sierra Leone</a></p>\n\n<p>Guinea-Bissau - apply through <a rel=\"external\" href=\"https://uk.tlscontact.com/sn/dkr/splash.php\">Senegal</a></p>\n\n<p><a rel=\"external\" href=\"https://visa.vfsglobal.com/guy/en/gbr/attend-centre\">Guyana</a></p>\n\n<h2 id=\"h\">H</h2>\n\n<p>Haiti - apply through the <a rel=\"external\" href=\"https://visa.vfsglobal.com/dom/en/gbr/attend-centre\">Dominican Republic</a></p>\n\n<p><a rel=\"external\" href=\"https://visa.vfsglobal.com/hnd/en/gbr/attend-centre\">Honduras</a></p>\n\n<p><a rel=\"external\" href=\"https://visa.vfsglobal.com/hkg/en/gbr/attend-centre\">Hong Kong</a></p>\n\n<p><a rel=\"external\" href=\"https://uk.tlscontact.com/hu/bud/splash.php\">Hungary</a></p>\n\n<h2 id=\"i\">I</h2>\n\n<p><a rel=\"external\" href=\"https://uk.tlscontact.com/is/rkv/splash.php\">Iceland</a></p>\n\n<p><a rel=\"external\" href=\"https://visa.vfsglobal.com/ind/en/gbr/attend-centre\">India</a></p>\n\n<p><a rel=\"external\" href=\"https://visa.vfsglobal.com/idn/en/gbr/attend-centre\">Indonesia</a></p>\n\n<p><a rel=\"external\" href=\"https://visa.vfsglobal.com/irn/en/gbr/attend-centre\">Iran</a></p>\n\n<p><a rel=\"external\" href=\"https://uk.tlscontact.com/iq/bgw/splash.php\">Iraq</a></p>\n\n<p><a rel=\"external\" href=\"https://uk.tlscontact.com/ie/dub/splash.php\">Ireland</a></p>\n\n<p><a rel=\"external\" href=\"https://uk.tlscontact.com/il/tlv/splash.php\">Israel</a></p>\n\n<p><a rel=\"external\" href=\"https://uk.tlscontact.com/it/rom/splash.php\">Italy</a></p>\n\n<p><a rel=\"external\" href=\"https://uk.tlscontact.com/ci/abj/splash.php\">Ivory Coast</a></p>\n\n<h2 id=\"j\">J</h2>\n\n<p><a rel=\"external\" href=\"https://visa.vfsglobal.com/jam/en/gbr/attend-centre\">Jamaica</a></p>\n\n<p><a rel=\"external\" href=\"https://visa.vfsglobal.com/jpn/en/gbr/attend-centre\">Japan</a></p>\n\n<p><a rel=\"external\" href=\"https://uk.tlscontact.com/jo/amm/splash.php\">Jordan</a></p>\n\n<h2 id=\"k\">K</h2>\n\n<p><a rel=\"external\" href=\"https://uk.tlscontact.com/kz/ala/splash.php\">Kazakhstan</a></p>\n\n<p><a rel=\"external\" href=\"https://uk.tlscontact.com/ke/mba/splash.php\">Kenya</a></p>\n\n<p>Kiribati - apply through <a rel=\"external\" href=\"https://visa.vfsglobal.com/fji/en/gbr/attend-centre\">Fiji</a></p>\n\n<p><a rel=\"external\" href=\"https://uk.tlscontact.com/xk/prn/splash.php\">Kosovo</a></p>\n\n<p><a rel=\"external\" href=\"https://visa.vfsglobal.com/kwt/en/gbr/attend-centre\">Kuwait</a></p>\n\n<p><a rel=\"external\" href=\"https://uk.tlscontact.com/kg/fru/splash.php\">Kyrgyzstan</a></p>\n\n<h2 id=\"l\">L</h2>\n\n<p><a rel=\"external\" href=\"https://visa.vfsglobal.com/lao/en/gbr/attend-centre\">Laos</a></p>\n\n<p><a rel=\"external\" href=\"https://uk.tlscontact.com/lv/rix/splash.php\">Latvia</a></p>\n\n<p><a rel=\"external\" href=\"https://uk.tlscontact.com/lb/bey/splash.php\">Lebanon</a></p>\n\n<p>Lesotho - apply through <a rel=\"external\" href=\"https://uk.tlscontact.com/za/cpt/splash.php\">South Africa</a></p>\n\n<p>Liberia - apply at your nearest accessible visa application centre in West Africa</p>\n\n<p>Libya - apply through <a rel=\"external\" href=\"https://uk.tlscontact.com/mt/mla/splash.php\">Malta</a> or <a rel=\"external\" href=\"https://uk.tlscontact.com/tn/tun/splash.php\">Tunisia</a></p>\n\n<p>Liechtenstein - apply through <a rel=\"external\" href=\"https://uk.tlscontact.com/ch/gen/splash.php\">Switzerland</a></p>\n\n<p><a rel=\"external\" href=\"https://uk.tlscontact.com/lt/vno/index.php\">Lithuania</a></p>\n\n<p>Luxembourg - apply through <a rel=\"external\" href=\"https://uk.tlscontact.com/fr/par/splash.php\">France</a></p>\n\n<h2 id=\"m\">M</h2>\n\n<p>Macau - apply through <a rel=\"external\" href=\"https://visa.vfsglobal.com/hkg/en/gbr/attend-centre\">Hong Kong</a></p>\n\n<p><a rel=\"external\" href=\"https://uk.tlscontact.com/mk/skp/splash.php\">Macedonia</a></p>\n\n<p><a rel=\"external\" href=\"https://uk.tlscontact.com/mg/tnr/splash.php\">Madagascar</a></p>\n\n<p><a rel=\"external\" href=\"https://uk.tlscontact.com/mw/llw/splash.php\">Malawi</a></p>\n\n<p><a rel=\"external\" href=\"https://visa.vfsglobal.com/mys/en/gbr/attend-centre\">Malaysia</a></p>\n\n<p>Maldives - apply through <a rel=\"external\" href=\"https://visa.vfsglobal.com/lka/en/gbr/attend-centre\">Sri Lanka</a></p>\n\n<p>Mali - apply through <a rel=\"external\" href=\"https://uk.tlscontact.com/sn/dkr/splash.php\">Senegal</a></p>\n\n<p><a rel=\"external\" href=\"https://uk.tlscontact.com/mt/mla/splash.php\">Malta</a></p>\n\n<p>Marshall Islands - apply through <a rel=\"external\" href=\"https://visa.vfsglobal.com/fji/en/gbr/attend-centre\">Fiji</a></p>\n\n<p>Mauritania - apply through <a rel=\"external\" href=\"https://uk.tlscontact.com/ma/rba/splash.php\">Morocco</a></p>\n\n<p><a rel=\"external\" href=\"https://uk.tlscontact.com/mu/mru/splash.php\">Mauritius</a></p>\n\n<p><a rel=\"external\" href=\"https://visa.vfsglobal.com/mex/en/gbr/attend-centre\">Mexico</a></p>\n\n<p>Micronesia, Federated States of - apply through <a rel=\"external\" href=\"https://visa.vfsglobal.com/fji/en/gbr/attend-centre\">Fiji</a></p>\n\n<p><a rel=\"external\" href=\"https://uk.tlscontact.com/md/kiv/splash.php\">Moldova</a></p>\n\n<p>Monaco - apply through <a rel=\"external\" href=\"https://uk.tlscontact.com/fr/par/splash.php\">France</a></p>\n\n<p><a rel=\"external\" href=\"https://visa.vfsglobal.com/mng/en/gbr/attend-centre\">Mongolia</a></p>\n\n<p><a rel=\"external\" href=\"https://uk.tlscontact.com/me/tgd/splash.php\">Montenegro</a></p>\n\n<p>Montserrat - apply through <a rel=\"external\" href=\"https://visa.vfsglobal.com/brb/en/gbr/attend-centre\">Barbados</a></p>\n\n<p><a rel=\"external\" href=\"https://uk.tlscontact.com/ma/rba/splash.php\">Morocco</a></p>\n\n<p><a rel=\"external\" href=\"https://uk.tlscontact.com/mz/mpm/splash.php\">Mozambique</a></p>\n\n<p><a rel=\"external\" href=\"https://visa.vfsglobal.com/mmr/en/gbr/attend-centre\">Myanmar (Burma)</a></p>\n\n<h2 id=\"n\">N</h2>\n\n<p><a rel=\"external\" href=\"https://uk.tlscontact.com/na/wdh/splash.php\">Namibia</a></p>\n\n<p>Nauru - apply through <a rel=\"external\" href=\"https://visa.vfsglobal.com/fji/en/gbr/attend-centre\">Fiji</a></p>\n\n<p><a rel=\"external\" href=\"https://visa.vfsglobal.com/npl/en/gbr/attend-centre\">Nepal</a></p>\n\n<p><a rel=\"external\" href=\"https://uk.tlscontact.com/nl/ams/splash.php\">Netherlands</a></p>\n\n<p><a rel=\"external\" href=\"https://visa.vfsglobal.com/nzl/en/gbr/attend-centre\">New Zealand</a></p>\n\n<p>Nicaragua - apply at your nearest accessible visa application centre in the Americas</p>\n\n<p>Niger - apply through <a rel=\"external\" href=\"https://uk.tlscontact.com/gh/acc/splash.php\">Ghana</a> or <a rel=\"external\" href=\"https://uk.tlscontact.com/ci/abj/splash.php\">Ivory Coast</a></p>\n\n<p><a rel=\"external\" href=\"https://uk.tlscontact.com/ng/abv/splash.php\">Nigeria</a></p>\n\n<p>North Korea - apply through <a rel=\"external\" href=\"https://visa.vfsglobal.com/chn/en/gbr/attend-centre\">China</a></p>\n\n<p><a rel=\"external\" href=\"https://uk.tlscontact.com/no/osl/splash.php\">Norway</a></p>\n\n<h2 id=\"o\">O</h2>\n\n<p><a rel=\"external\" href=\"https://visa.vfsglobal.com/omn/en/gbr/attend-centre\">Oman</a></p>\n\n<h2 id=\"p\">P</h2>\n\n<p>The Occupied Palestinian Territories - apply at your nearest accessible visa application centre</p>\n\n<p><a rel=\"external\" href=\"https://visa.vfsglobal.com/pak/en/gbr/attend-centre\">Pakistan</a></p>\n\n<p>Palau - apply through <a rel=\"external\" href=\"https://visa.vfsglobal.com/phl/en/gbr/attend-centre\">Philippines</a></p>\n\n<p><a rel=\"external\" href=\"https://visa.vfsglobal.com/pan/en/gbr/attend-centre\">Panama</a></p>\n\n<p><a rel=\"external\" href=\"https://visa.vfsglobal.com/png/en/gbr/attend-centre\">Papua New Guinea</a></p>\n\n<p>Paraguay - apply through <a rel=\"external\" href=\"https://visa.vfsglobal.com/arg/en/gbr/attend-centre\">Argentina</a></p>\n\n<p><a rel=\"external\" href=\"https://visa.vfsglobal.com/per/en/gbr/attend-centre\">Peru</a></p>\n\n<p><a rel=\"external\" href=\"https://visa.vfsglobal.com/phl/en/gbr/attend-centre\">Philippines</a></p>\n\n<p>Pitcairn, Henderson, Dulcie and Oeno Islands - apply at your nearest accessible visa application centre</p>\n\n<p><a rel=\"external\" href=\"https://uk.tlscontact.com/pl/waw/splash.php\">Poland</a></p>\n\n<p><a rel=\"external\" href=\"https://uk.tlscontact.com/pt/lis/splash.php\">Portugal</a></p>\n\n<h2 id=\"q\">Q</h2>\n\n<p><a rel=\"external\" href=\"https://visa.vfsglobal.com/qat/en/gbr/attend-centre\">Qatar</a></p>\n\n<h2 id=\"r\">R</h2>\n\n<p><a rel=\"external\" href=\"https://uk.tlscontact.com/ro/bbu/splash.php\">Romania</a></p>\n\n<p><a rel=\"external\" href=\"https://uk.tlscontact.com/ru/eka/splash.php\">Russia</a></p>\n\n<p><a rel=\"external\" href=\"https://uk.tlscontact.com/rw/kgl/splash.php\">Rwanda</a></p>\n\n<h2 id=\"s\">S</h2>\n\n<p>Samoa and Western Samoa - apply through <a rel=\"external\" href=\"https://visa.vfsglobal.com/fji/en/gbr/attend-centre\">Fiji</a></p>\n\n<p>San Marino - apply through <a rel=\"external\" href=\"https://uk.tlscontact.com/it/rom/splash.php\">Italy</a></p>\n\n<p>São Tomé and Principe - apply through <a rel=\"external\" href=\"https://uk.tlscontact.com/ao/lad/splash.php\">Angola</a></p>\n\n<p><a rel=\"external\" href=\"https://visa.vfsglobal.com/sau/en/gbr/attend-centre\">Saudi Arabia</a></p>\n\n<p><a rel=\"external\" href=\"https://uk.tlscontact.com/sn/dkr/splash.php\">Senegal</a></p>\n\n<p><a rel=\"external\" href=\"https://uk.tlscontact.com/rs/beg/splash.php\">Serbia</a></p>\n\n<p>Seychelles - apply through <a rel=\"external\" href=\"https://uk.tlscontact.com/mu/mru/splash.php\">Mauritius</a></p>\n\n<p><a rel=\"external\" href=\"https://uk.tlscontact.com/sl/fna/splash.php\">Sierra Leone</a></p>\n\n<p><a rel=\"external\" href=\"https://visa.vfsglobal.com/sgp/en/gbr/attend-centre\">Singapore</a></p>\n\n<p>Slovakia – apply at your nearest accessible visa application centre</p>\n\n<p><a rel=\"external\" href=\"https://uk.tlscontact.com/si/lju/splash.php\">Slovenia</a></p>\n\n<p>Solomon Islands - apply through <a rel=\"external\" href=\"https://visa.vfsglobal.com/png/en/gbr/attend-centre\">Papua New Guinea</a></p>\n\n<p>Somalia - apply through <a rel=\"external\" href=\"https://uk.tlscontact.com/ke/mba/splash.php\">Kenya</a></p>\n\n<p><a rel=\"external\" href=\"https://uk.tlscontact.com/za/cpt/splash.php\">South Africa</a></p>\n\n<p><a rel=\"external\" href=\"https://visa.vfsglobal.com/kor/en/gbr/attend-centre\">South Korea</a></p>\n\n<p>South Sudan - apply through <a rel=\"external\" href=\"https://uk.tlscontact.com/ke/mba/splash.php\">Kenya</a></p>\n\n<p><a rel=\"external\" href=\"https://uk.tlscontact.com/es/mad/splash.php\">Spain</a></p>\n\n<p><a rel=\"external\" href=\"https://visa.vfsglobal.com/lka/en/gbr/attend-centre\">Sri Lanka</a></p>\n\n<p><a href=\"/government/publications/st-helena-apply-for-a-uk-visa\">St Helena</a></p>\n\n<p>St Kitts and Nevis - apply through <a rel=\"external\" href=\"https://visa.vfsglobal.com/brb/en/gbr/attend-centre\">Barbados</a></p>\n\n<p><a rel=\"external\" href=\"https://visa.vfsglobal.com/lca/en/gbr/attend-centre\">St Lucia</a></p>\n\n<p>St Vincent and The Grenadines - apply through <a rel=\"external\" href=\"https://visa.vfsglobal.com/brb/en/gbr/attend-centre\">Barbados</a></p>\n\n<p><a rel=\"external\" href=\"https://uk.tlscontact.com/sd/krt/splash.php\">Sudan</a> -  apply at your nearest accessible visa application centre</p>\n\n<p><a rel=\"external\" href=\"https://visa.vfsglobal.com/sur/en/gbr\">Suriname</a></p>\n\n<p><a rel=\"external\" href=\"https://uk.tlscontact.com/se/bma/splash.php\">Sweden</a></p>\n\n<p><a rel=\"external\" href=\"https://uk.tlscontact.com/ch/gen/splash.php\">Switzerland</a></p>\n\n<p>Syria – apply through <a rel=\"external\" href=\"https://uk.tlscontact.com/lb/bey/splash.php\">Lebanon</a> or <a rel=\"external\" href=\"https://uk.tlscontact.com/jo/amm/splash.php\">Jordan</a></p>\n\n<h2 id=\"t\">T</h2>\n\n<p><a rel=\"external\" href=\"https://visa.vfsglobal.com/twn/en/gbr/attend-centre\">Taiwan</a></p>\n\n<p><a rel=\"external\" href=\"https://uk.tlscontact.com/tj/dyu/splash.php\">Tajikistan</a></p>\n\n<p><a rel=\"external\" href=\"https://uk.tlscontact.com/tz/dar/splash.php\">Tanzania</a></p>\n\n<p><a rel=\"external\" href=\"https://visa.vfsglobal.com/tha/en/gbr/attend-centre\">Thailand</a></p>\n\n<p>Togo - apply through <a rel=\"external\" href=\"https://uk.tlscontact.com/gh/acc/splash.php\">Ghana</a></p>\n\n<p>Tonga - apply through <a rel=\"external\" href=\"https://visa.vfsglobal.com/fji/en/gbr/attend-centre\">Fiji</a></p>\n\n<p><a rel=\"external\" href=\"https://visa.vfsglobal.com/tto/en/gbr/attend-centre\">Trinidad and Tobago</a></p>\n\n<p>Tristan da Cunha - apply through <a href=\"/government/publications/st-helena-apply-for-a-uk-visa\">St. Helena</a></p>\n\n<p><a rel=\"external\" href=\"https://uk.tlscontact.com/tn/tun/splash.php\">Tunisia</a></p>\n\n<p><a rel=\"external\" href=\"https://uk.tlscontact.com/tr/ada/splash.php\">Turkey</a></p>\n\n<p><a rel=\"external\" href=\"https://uk.tlscontact.com/tm/asb/splash.php\">Turkmenistan</a></p>\n\n<p>Turks and Caicos Islands - apply through <a rel=\"external\" href=\"https://visa.vfsglobal.com/brb/en/gbr/attend-centre\">Barbados</a></p>\n\n<p>Tuvalu - apply through <a rel=\"external\" href=\"https://visa.vfsglobal.com/fji/en/gbr/attend-centre\">Fiji</a></p>\n\n<h2 id=\"u\">U</h2>\n\n<p><a rel=\"external\" href=\"https://uk.tlscontact.com/ug/kla/splash.php\">Uganda</a></p>\n\n<p><a rel=\"external\" href=\"https://pos.tlscontact.com/kbp_en/home\">Ukraine</a> – the Ukraine visa application centre is open for providing your fingerprints and photo (‘biometric information’) and document scanning only</p>\n\n<p><a rel=\"external\" href=\"https://visa.vfsglobal.com/are/en/gbr/attend-centre\">United Arab Emirates</a></p>\n\n<p>Uruguay - apply through <a rel=\"external\" href=\"https://visa.vfsglobal.com/arg/en/gbr/attend-centre\">Argentina</a></p>\n\n<p><a rel=\"external\" href=\"https://visa.vfsglobal.com/usa/en/gbr/attend-centre\">USA</a></p>\n\n<p><a rel=\"external\" href=\"https://uk.tlscontact.com/uz/tas/splash.php\">Uzbekistan</a></p>\n\n<h2 id=\"v\">V</h2>\n\n<p><a rel=\"external\" href=\"https://visa.vfsglobal.com/vut/en/gbr/attend-centre\">Vanuatu</a></p>\n\n<p>Vatican City - apply through <a rel=\"external\" href=\"https://uk.tlscontact.com/it/rom/splash.php\">Italy</a></p>\n\n<p><a rel=\"external\" href=\"https://visa.vfsglobal.com/ven/en/gbr/attend-centre\">Venezuela</a></p>\n\n<p><a rel=\"external\" href=\"https://visa.vfsglobal.com/vnm/en/gbr/attend-centre\">Vietnam</a></p>\n\n<h2 id=\"w\">W</h2>\n\n<p>Western Sahara - apply through <a rel=\"external\" href=\"https://uk.tlscontact.com/ma/rba/splash.php\">Morocco</a></p>\n\n<h2 id=\"y\">Y</h2>\n\n<p>Yemen - apply through <a rel=\"external\" href=\"https://pos.tlscontact.com/amm_en/index.php\">Jordan</a></p>\n\n<h2 id=\"z\">Z</h2>\n\n<p><a rel=\"external\" href=\"https://uk.tlscontact.com/zm/lun/splash.php\">Zambia</a></p>\n\n<p><a rel=\"external\" href=\"https://uk.tlscontact.com/zw/hre/splash.php\">Zimbabwe</a></p>\n",
    "external_related_links": [

    ]
  },
  "document_type": "answer",
  "first_published_at": "2014-02-21T19:36:08Z",
  "links": {
    "available_translations": [
      {
        "api_path": "/api/content/find-a-visa-application-centre",
        "api_url": "https://www.gov.uk/api/content/find-a-visa-application-centre",
        "base_path": "/find-a-visa-application-centre",
        "content_id": "aa055bd6-fde1-4471-8ac2-ac86241b4898",
        "document_type": "answer",
        "links": {
        },
        "locale": "en",
        "public_updated_at": "2014-11-24T17:50:24Z",
        "schema_name": "answer",
        "title": "Find a visa application centre",
        "web_url": "https://www.gov.uk/find-a-visa-application-centre",
        "withdrawn": false
      }
    ],
    "ordered_related_items": [
      {
        "api_path": "/api/content/check-uk-visa",
        "api_url": "https://www.gov.uk/api/content/check-uk-visa",
        "base_path": "/check-uk-visa",
        "content_id": "dc1a1744-4089-43b3-b2e3-4e397b6b15b1",
        "document_type": "smart_answer",
        "links": {
          "mainstream_browse_pages": [
            {
              "api_path": "/api/content/browse/visas-immigration/commonwealth-british-nationals-overseas",
              "api_url": "https://www.gov.uk/api/content/browse/visas-immigration/commonwealth-british-nationals-overseas",
              "base_path": "/browse/visas-immigration/commonwealth-british-nationals-overseas",
              "content_id": "2aaa0deb-65be-407c-b331-807c54ded5c1",
              "description": "BNO visa, right of abode, UK Ancestry visa",
              "document_type": "mainstream_browse_page",
              "links": {
                "parent": [
                  {
                    "api_path": "/api/content/browse/visas-immigration",
                    "api_url": "https://www.gov.uk/api/content/browse/visas-immigration",
                    "base_path": "/browse/visas-immigration",
                    "content_id": "df6fcdc4-62bc-4e05-90e3-cb2e452453a4",
                    "description": "Apply to visit, work, study, settle or seek asylum in the UK",
                    "document_type": "mainstream_browse_page",
                    "links": {
                    },
                    "locale": "en",
                    "public_updated_at": "2021-06-03T13:56:26Z",
                    "schema_name": "mainstream_browse_page",
                    "title": "Visas and immigration",
                    "web_url": "https://www.gov.uk/browse/visas-immigration",
                    "withdrawn": false
                  }
                ]
              },
              "locale": "en",
              "public_updated_at": "2022-12-21T09:01:45Z",
              "schema_name": "mainstream_browse_page",
              "title": "Commonwealth citizens and British nationals (overseas)",
              "web_url": "https://www.gov.uk/browse/visas-immigration/commonwealth-british-nationals-overseas",
              "withdrawn": false
            },
            {
              "api_path": "/api/content/browse/visas-immigration/eu-eea-swiss",
              "api_url": "https://www.gov.uk/api/content/browse/visas-immigration/eu-eea-swiss",
              "base_path": "/browse/visas-immigration/eu-eea-swiss",
              "content_id": "16e8b371-acd2-4b1b-a8a1-a430b04cb475",
              "description": "Settled and pre-settled status, EU Settlement Scheme family permit, Frontier Worker permit",
              "document_type": "mainstream_browse_page",
              "links": {
                "parent": [
                  {
                    "api_path": "/api/content/browse/visas-immigration",
                    "api_url": "https://www.gov.uk/api/content/browse/visas-immigration",
                    "base_path": "/browse/visas-immigration",
                    "content_id": "df6fcdc4-62bc-4e05-90e3-cb2e452453a4",
                    "description": "Apply to visit, work, study, settle or seek asylum in the UK",
                    "document_type": "mainstream_browse_page",
                    "links": {
                    },
                    "locale": "en",
                    "public_updated_at": "2021-06-03T13:56:26Z",
                    "schema_name": "mainstream_browse_page",
                    "title": "Visas and immigration",
                    "web_url": "https://www.gov.uk/browse/visas-immigration",
                    "withdrawn": false
                  }
                ]
              },
              "locale": "en",
              "public_updated_at": "2022-12-21T09:01:45Z",
              "schema_name": "mainstream_browse_page",
              "title": "EU, EEA and Swiss citizens",
              "web_url": "https://www.gov.uk/browse/visas-immigration/eu-eea-swiss",
              "withdrawn": false
            },
            {
              "api_path": "/api/content/browse/visas-immigration/family-visas",
              "api_url": "https://www.gov.uk/api/content/browse/visas-immigration/family-visas",
              "base_path": "/browse/visas-immigration/family-visas",
              "content_id": "ea1f74cd-7c16-48d8-bf79-1a45b80508ef",
              "description": "Partner, spouse, dependant and family member visas and permits",
              "document_type": "mainstream_browse_page",
              "links": {
                "parent": [
                  {
                    "api_path": "/api/content/browse/visas-immigration",
                    "api_url": "https://www.gov.uk/api/content/browse/visas-immigration",
                    "base_path": "/browse/visas-immigration",
                    "content_id": "df6fcdc4-62bc-4e05-90e3-cb2e452453a4",
                    "description": "Apply to visit, work, study, settle or seek asylum in the UK",
                    "document_type": "mainstream_browse_page",
                    "links": {
                    },
                    "locale": "en",
                    "public_updated_at": "2021-06-03T13:56:26Z",
                    "schema_name": "mainstream_browse_page",
                    "title": "Visas and immigration",
                    "web_url": "https://www.gov.uk/browse/visas-immigration",
                    "withdrawn": false
                  }
                ]
              },
              "locale": "en",
              "public_updated_at": "2022-12-21T09:00:26Z",
              "schema_name": "mainstream_browse_page",
              "title": "Family in the UK",
              "web_url": "https://www.gov.uk/browse/visas-immigration/family-visas",
              "withdrawn": false
            },
            {
              "api_path": "/api/content/browse/visas-immigration/student-visas",
              "api_url": "https://www.gov.uk/api/content/browse/visas-immigration/student-visas",
              "base_path": "/browse/visas-immigration/student-visas",
              "content_id": "f63075f3-d3a1-40d0-846e-6c3330263535",
              "description": "Student visas for courses, degrees and independent schools",
              "document_type": "mainstream_browse_page",
              "links": {
                "parent": [
                  {
                    "api_path": "/api/content/browse/visas-immigration",
                    "api_url": "https://www.gov.uk/api/content/browse/visas-immigration",
                    "base_path": "/browse/visas-immigration",
                    "content_id": "df6fcdc4-62bc-4e05-90e3-cb2e452453a4",
                    "description": "Apply to visit, work, study, settle or seek asylum in the UK",
                    "document_type": "mainstream_browse_page",
                    "links": {
                    },
                    "locale": "en",
                    "public_updated_at": "2021-06-03T13:56:26Z",
                    "schema_name": "mainstream_browse_page",
                    "title": "Visas and immigration",
                    "web_url": "https://www.gov.uk/browse/visas-immigration",
                    "withdrawn": false
                  }
                ]
              },
              "locale": "en",
              "public_updated_at": "2023-11-29T10:46:30Z",
              "schema_name": "mainstream_browse_page",
              "title": "Study in the UK",
              "web_url": "https://www.gov.uk/browse/visas-immigration/student-visas",
              "withdrawn": false
            },
            {
              "api_path": "/api/content/browse/visas-immigration/arriving-in-the-uk",
              "api_url": "https://www.gov.uk/api/content/browse/visas-immigration/arriving-in-the-uk",
              "base_path": "/browse/visas-immigration/arriving-in-the-uk",
              "content_id": "2d9903ac-4194-4034-a53b-30d768f4fafb",
              "description": "Moving your belongings, going through customs and tax",
              "document_type": "mainstream_browse_page",
              "links": {
                "parent": [
                  {
                    "api_path": "/api/content/browse/visas-immigration",
                    "api_url": "https://www.gov.uk/api/content/browse/visas-immigration",
                    "base_path": "/browse/visas-immigration",
                    "content_id": "df6fcdc4-62bc-4e05-90e3-cb2e452453a4",
                    "description": "Apply to visit, work, study, settle or seek asylum in the UK",
                    "document_type": "mainstream_browse_page",
                    "links": {
                    },
                    "locale": "en",
                    "public_updated_at": "2021-06-03T13:56:26Z",
                    "schema_name": "mainstream_browse_page",
                    "title": "Visas and immigration",
                    "web_url": "https://www.gov.uk/browse/visas-immigration",
                    "withdrawn": false
                  }
                ]
              },
              "locale": "en",
              "public_updated_at": "2023-09-22T09:45:51Z",
              "schema_name": "mainstream_browse_page",
              "title": "Travelling to the UK",
              "web_url": "https://www.gov.uk/browse/visas-immigration/arriving-in-the-uk",
              "withdrawn": false
            },
            {
              "api_path": "/api/content/browse/visas-immigration/tourist-short-stay-visas",
              "api_url": "https://www.gov.uk/api/content/browse/visas-immigration/tourist-short-stay-visas",
              "base_path": "/browse/visas-immigration/tourist-short-stay-visas",
              "content_id": "749762c5-0e80-4d04-b766-9850192764d4",
              "description": "Visit for tourism, business or a short stay (up to 6 months), airport transit visas",
              "document_type": "mainstream_browse_page",
              "links": {
                "parent": [
                  {
                    "api_path": "/api/content/browse/visas-immigration",
                    "api_url": "https://www.gov.uk/api/content/browse/visas-immigration",
                    "base_path": "/browse/visas-immigration",
                    "content_id": "df6fcdc4-62bc-4e05-90e3-cb2e452453a4",
                    "description": "Apply to visit, work, study, settle or seek asylum in the UK",
                    "document_type": "mainstream_browse_page",
                    "links": {
                    },
                    "locale": "en",
                    "public_updated_at": "2021-06-03T13:56:26Z",
                    "schema_name": "mainstream_browse_page",
                    "title": "Visas and immigration",
                    "web_url": "https://www.gov.uk/browse/visas-immigration",
                    "withdrawn": false
                  }
                ]
              },
              "locale": "en",
              "public_updated_at": "2022-12-21T09:00:41Z",
              "schema_name": "mainstream_browse_page",
              "title": "Visit the UK",
              "web_url": "https://www.gov.uk/browse/visas-immigration/tourist-short-stay-visas",
              "withdrawn": false
            },
            {
              "api_path": "/api/content/browse/visas-immigration/what-you-need-to-do",
              "api_url": "https://www.gov.uk/api/content/browse/visas-immigration/what-you-need-to-do",
              "base_path": "/browse/visas-immigration/what-you-need-to-do",
              "content_id": "8ff60b56-b0e8-4019-af4c-80ca1ad04c29",
              "description": "Check if you need a UK visa, how to apply, sign in, manage your application, biometric residence permits (BRPs), share codes",
              "document_type": "mainstream_browse_page",
              "links": {
                "parent": [
                  {
                    "api_path": "/api/content/browse/visas-immigration",
                    "api_url": "https://www.gov.uk/api/content/browse/visas-immigration",
                    "base_path": "/browse/visas-immigration",
                    "content_id": "df6fcdc4-62bc-4e05-90e3-cb2e452453a4",
                    "description": "Apply to visit, work, study, settle or seek asylum in the UK",
                    "document_type": "mainstream_browse_page",
                    "links": {
                    },
                    "locale": "en",
                    "public_updated_at": "2021-06-03T13:56:26Z",
                    "schema_name": "mainstream_browse_page",
                    "title": "Visas and immigration",
                    "web_url": "https://www.gov.uk/browse/visas-immigration",
                    "withdrawn": false
                  }
                ]
              },
              "locale": "en",
              "public_updated_at": "2022-12-21T12:05:51Z",
              "schema_name": "mainstream_browse_page",
              "title": "What you need to do",
              "web_url": "https://www.gov.uk/browse/visas-immigration/what-you-need-to-do",
              "withdrawn": false
            },
            {
              "api_path": "/api/content/browse/visas-immigration/work-visas",
              "api_url": "https://www.gov.uk/api/content/browse/visas-immigration/work-visas",
              "base_path": "/browse/visas-immigration/work-visas",
              "content_id": "4ab4764d-d9ce-425f-a8cc-aaba4a38be09",
              "description": "Skilled Worker visa, Graduate visa, other work visas, right to work",
              "document_type": "mainstream_browse_page",
              "links": {
                "parent": [
                  {
                    "api_path": "/api/content/browse/visas-immigration",
                    "api_url": "https://www.gov.uk/api/content/browse/visas-immigration",
                    "base_path": "/browse/visas-immigration",
                    "content_id": "df6fcdc4-62bc-4e05-90e3-cb2e452453a4",
                    "description": "Apply to visit, work, study, settle or seek asylum in the UK",
                    "document_type": "mainstream_browse_page",
                    "links": {
                    },
                    "locale": "en",
                    "public_updated_at": "2021-06-03T13:56:26Z",
                    "schema_name": "mainstream_browse_page",
                    "title": "Visas and immigration",
                    "web_url": "https://www.gov.uk/browse/visas-immigration",
                    "withdrawn": false
                  }
                ]
              },
              "locale": "en",
              "public_updated_at": "2023-07-13T12:27:58Z",
              "schema_name": "mainstream_browse_page",
              "title": "Work in the UK",
              "web_url": "https://www.gov.uk/browse/visas-immigration/work-visas",
              "withdrawn": false
            }
          ]
        },
        "locale": "en",
        "public_updated_at": "2021-06-16T08:18:46Z",
        "schema_name": "smart_answer",
        "title": "Check if you need a UK visa",
        "web_url": "https://www.gov.uk/check-uk-visa",
        "withdrawn": false
      },
      {
        "api_path": "/api/content/tb-test-visa",
        "api_url": "https://www.gov.uk/api/content/tb-test-visa",
        "base_path": "/tb-test-visa",
        "content_id": "fa7bb7fd-b4bc-45a2-8958-1f0bfa4c3e56",
        "document_type": "guide",
        "links": {
          "mainstream_browse_pages": [
            {
              "api_path": "/api/content/browse/visas-immigration/what-you-need-to-do",
              "api_url": "https://www.gov.uk/api/content/browse/visas-immigration/what-you-need-to-do",
              "base_path": "/browse/visas-immigration/what-you-need-to-do",
              "content_id": "8ff60b56-b0e8-4019-af4c-80ca1ad04c29",
              "description": "Check if you need a UK visa, how to apply, sign in, manage your application, biometric residence permits (BRPs), share codes",
              "document_type": "mainstream_browse_page",
              "links": {
                "parent": [
                  {
                    "api_path": "/api/content/browse/visas-immigration",
                    "api_url": "https://www.gov.uk/api/content/browse/visas-immigration",
                    "base_path": "/browse/visas-immigration",
                    "content_id": "df6fcdc4-62bc-4e05-90e3-cb2e452453a4",
                    "description": "Apply to visit, work, study, settle or seek asylum in the UK",
                    "document_type": "mainstream_browse_page",
                    "links": {
                    },
                    "locale": "en",
                    "public_updated_at": "2021-06-03T13:56:26Z",
                    "schema_name": "mainstream_browse_page",
                    "title": "Visas and immigration",
                    "web_url": "https://www.gov.uk/browse/visas-immigration",
                    "withdrawn": false
                  }
                ]
              },
              "locale": "en",
              "public_updated_at": "2022-12-21T12:05:51Z",
              "schema_name": "mainstream_browse_page",
              "title": "What you need to do",
              "web_url": "https://www.gov.uk/browse/visas-immigration/what-you-need-to-do",
              "withdrawn": false
            }
          ]
        },
        "locale": "en",
        "public_updated_at": "2015-01-07T15:58:35Z",
        "schema_name": "guide",
        "title": "Tuberculosis tests for visa applicants",
        "web_url": "https://www.gov.uk/tb-test-visa",
        "withdrawn": false
      }
    ],
    "organisations": [
      {
        "analytics_identifier": "OT554",
        "api_path": "/api/content/government/organisations/uk-visas-and-immigration",
        "api_url": "https://www.gov.uk/api/content/government/organisations/uk-visas-and-immigration",
        "base_path": "/government/organisations/uk-visas-and-immigration",
        "content_id": "04148522-b0c1-4137-b687-5f3c3bdd561a",
        "details": {
          "acronym": "UKVI",
          "brand": "home-office",
          "default_news_image": null,
          "logo": {
            "crest": "ho",
            "formatted_title": "UK Visas and Immigration"
          },
          "organisation_govuk_status": {
            "status": "live",
            "updated_at": null,
            "url": null
          }
        },
        "document_type": "organisation",
        "links": {
        },
        "locale": "en",
        "schema_name": "organisation",
        "title": "UK Visas and Immigration",
        "web_url": "https://www.gov.uk/government/organisations/uk-visas-and-immigration",
        "withdrawn": false
      }
    ],
    "primary_publishing_organisation": [
      {
        "analytics_identifier": "OT1056",
        "api_path": "/api/content/government/organisations/government-digital-service",
        "api_url": "https://www.gov.uk/api/content/government/organisations/government-digital-service",
        "base_path": "/government/organisations/government-digital-service",
        "content_id": "af07d5a5-df63-4ddc-9383-6a666845ebe9",
        "details": {
          "acronym": "GDS",
          "brand": "cabinet-office",
          "default_news_image": null,
          "logo": {
            "crest": "single-identity",
            "formatted_title": "Government Digital Service"
          },
          "organisation_govuk_status": {
            "status": "live",
            "updated_at": null,
            "url": null
          }
        },
        "document_type": "organisation",
        "links": {
        },
        "locale": "en",
        "schema_name": "organisation",
        "title": "Government Digital Service",
        "web_url": "https://www.gov.uk/government/organisations/government-digital-service",
        "withdrawn": false
      }
    ],
    "related_to_step_navs": [
      {
        "api_path": "/api/content/apply-marriage-visitor-visa",
        "api_url": "https://www.gov.uk/api/content/apply-marriage-visitor-visa",
        "base_path": "/apply-marriage-visitor-visa",
        "content_id": "8424e3fa-df5e-43e6-9158-59a8a18e1c8e",
        "details": {
          "step_by_step_nav": {
            "steps": [
              {
                "contents": [
                  {
                    "contents": [
                      {
                        "href": "/marriage-visa",
                        "text": "Check if you need a Marriage Visitor visa"
                      }
                    ],
                    "type": "list"
                  }
                ],
                "title": "Check if you need a visa"
              },
              {
                "contents": [
                  {
                    "contents": [
                      {
                        "href": "/marriage-visa/eligibility",
                        "text": "Check what you need to show evidence of"
                      },
                      {
                        "href": "/marriage-visa/documents-you-will-need",
                        "text": "Check what documents you can use as evidence"
                      }
                    ],
                    "type": "list"
                  }
                ],
                "title": "Prepare the evidence you need"
              },
              {
                "contents": [
                  {
                    "contents": [
                      {
                        "context": "£115",
                        "href": "/marriage-visa/apply",
                        "text": "Apply for a visa and book an appointment"
                      },
                      {
                        "href": "/find-a-visa-application-centre",
                        "text": "Check where your visa appointment will be"
                      }
                    ],
                    "type": "list"
                  },
                  {
                    "text": "You should get a decision within 3 weeks of your appointment. ",
                    "type": "paragraph"
                  },
                  {
                    "text": "You might be able to pay an extra £500 for a decision within 5 working days or £1,000 for a decision within 24 hours (not including weekends or bank holidays). Check with your visa application centre.",
                    "type": "paragraph"
                  }
                ],
                "title": "Apply"
              },
              {
                "contents": [
                  {
                    "contents": [
                      {
                        "href": "/marriage-visa/eligibility",
                        "text": "What you need to prove at your appointment"
                      }
                    ],
                    "type": "list"
                  },
                  {
                    "text": "At your appointment you’ll have your fingerprints and photograph (‘biometric information’) taken.",
                    "type": "paragraph"
                  },
                  {
                    "text": "After your appointment you'll be told when a decision has been made about your visa.",
                    "type": "paragraph"
                  }
                ],
                "title": "Attend an appointment"
              },
              {
                "contents": [
                  {
                    "contents": [
                      {
                        "href": "/uk-border-control/at-border-control",
                        "text": "Check what you need to show at the UK border"
                      },
                      {
                        "href": "/uk-border-control",
                        "text": "Check what you can bring with you"
                      }
                    ],
                    "type": "list"
                  },
                  {
                    "text": "Keep the documents that prove why you're visiting the UK in your hand luggage so you can show them if asked. ",
                    "type": "paragraph"
                  },
                  {
                    "contents": [
                      {
                        "href": "/marriage-visa/documents-you-will-need",
                        "text": "Check the documents you can use to show why you're visiting the UK"
                      }
                    ],
                    "type": "list"
                  },
                  {
                    "text": "Check your visa to find out when you must leave the UK. If you break the conditions of your visa you may not be able to return to the UK again.",
                    "type": "paragraph"
                  }
                ],
                "title": "Travel to the UK"
              }
            ],
            "title": "Apply for a Marriage Visitor visa: step by step"
          }
        },
        "document_type": "step_by_step_nav",
        "links": {
          "pages_related_to_step_nav": [
            {
              "api_path": "/api/content/find-a-visa-application-centre",
              "api_url": "https://www.gov.uk/api/content/find-a-visa-application-centre",
              "base_path": "/find-a-visa-application-centre",
              "content_id": "aa055bd6-fde1-4471-8ac2-ac86241b4898",
              "document_type": "answer",
              "links": {
              },
              "locale": "en",
              "public_updated_at": "2014-11-24T17:50:24Z",
              "schema_name": "answer",
              "title": "Find a visa application centre",
              "web_url": "https://www.gov.uk/find-a-visa-application-centre",
              "withdrawn": false
            }
          ]
        },
        "locale": "en",
        "public_updated_at": "2023-09-26T12:16:25Z",
        "schema_name": "step_by_step_nav",
        "title": "Apply for a Marriage Visitor visa: step by step",
        "web_url": "https://www.gov.uk/apply-marriage-visitor-visa",
        "withdrawn": false
      },
      {
        "api_path": "/api/content/apply-short-term-study-visa",
        "api_url": "https://www.gov.uk/api/content/apply-short-term-study-visa",
        "base_path": "/apply-short-term-study-visa",
        "content_id": "4ab05a9b-a933-4bb1-ae61-b9ab903b8805",
        "details": {
          "step_by_step_nav": {
            "steps": [
              {
                "contents": [
                  {
                    "text": "You might be eligible for different visas depending on why you're visiting the UK and how long for. ",
                    "type": "paragraph"
                  },
                  {
                    "contents": [
                      {
                        "href": "/check-uk-visa",
                        "text": "Check if you need a visa"
                      }
                    ],
                    "type": "list"
                  }
                ],
                "title": "Check if you need a visa"
              },
              {
                "contents": [
                  {
                    "contents": [
                      {
                        "href": "/study-visit-visa/eligibility",
                        "text": "Check what you need to show evidence of"
                      },
                      {
                        "href": "/study-visit-visa/documents-you-must-provide",
                        "text": "Check what documents you can use as evidence"
                      },
                      {
                        "href": "/tb-test-visa",
                        "text": "Check if you need a TB test to come to the UK"
                      }
                    ],
                    "type": "list"
                  }
                ],
                "title": "Prepare the evidence you need"
              },
              {
                "contents": [
                  {
                    "contents": [
                      {
                        "context": "£186",
                        "href": "/study-visit-visa/apply",
                        "text": "Apply for a visa and book an appointment"
                      },
                      {
                        "href": "/biometric-residence-permits",
                        "text": "Check if you'll need a biometric residence permit"
                      },
                      {
                        "href": "/find-a-visa-application-centre",
                        "text": "Check where your visa appointment will be"
                      }
                    ],
                    "type": "list"
                  },
                  {
                    "text": "You should get a decision within 3 weeks of your appointment. ",
                    "type": "paragraph"
                  },
                  {
                    "text": "You might be able to pay an extra £220 for a decision within 5 working days or £956 for a decision within 24 hours (not including weekends or bank holidays). Check with your visa application centre.",
                    "type": "paragraph"
                  }
                ],
                "title": "Apply"
              },
              {
                "contents": [
                  {
                    "contents": [
                      {
                        "href": "/study-visit-visa/eligibility",
                        "text": "What you need to prove at your appointment"
                      }
                    ],
                    "type": "list"
                  },
                  {
                    "text": "You'll be told when a decision has been made about your visa.",
                    "type": "paragraph"
                  }
                ],
                "title": "Attend an appointment"
              },
              {
                "contents": [
                  {
                    "contents": [
                      {
                        "href": "/uk-border-control/at-border-control",
                        "text": "Check what you need to show at the UK border"
                      },
                      {
                        "href": "/uk-border-control",
                        "text": "Check what you can bring with you"
                      }
                    ],
                    "type": "list"
                  },
                  {
                    "text": "Keep the documents that prove why you're visiting the UK in your hand luggage so you can show them if asked. ",
                    "type": "paragraph"
                  },
                  {
                    "contents": [
                      {
                        "href": "/study-visit-visa/documents-you-must-provide",
                        "text": "Check the documents you can use to show why you're visiting the UK"
                      }
                    ],
                    "type": "list"
                  }
                ],
                "title": "Travel to the UK"
              },
              {
                "contents": [
                  {
                    "text": "You'll need to collect your biometric residence permit soon after you arrive.",
                    "type": "paragraph"
                  },
                  {
                    "contents": [
                      {
                        "href": "/biometric-residence-permits/collect",
                        "text": "Collect your biometric residence permit"
                      }
                    ],
                    "type": "list"
                  },
                  {
                    "text": "Check your visa to find out when you must leave the UK. If you break the conditions of your visa you may not be able to return to the UK again.",
                    "type": "paragraph"
                  }
                ],
                "title": "After you arrive in the UK"
              }
            ],
            "title": "Apply for a Short-term study visa: step by step"
          }
        },
        "document_type": "step_by_step_nav",
        "links": {
          "pages_related_to_step_nav": [
            {
              "api_path": "/api/content/find-a-visa-application-centre",
              "api_url": "https://www.gov.uk/api/content/find-a-visa-application-centre",
              "base_path": "/find-a-visa-application-centre",
              "content_id": "aa055bd6-fde1-4471-8ac2-ac86241b4898",
              "document_type": "answer",
              "links": {
              },
              "locale": "en",
              "public_updated_at": "2014-11-24T17:50:24Z",
              "schema_name": "answer",
              "title": "Find a visa application centre",
              "web_url": "https://www.gov.uk/find-a-visa-application-centre",
              "withdrawn": false
            }
          ]
        },
        "locale": "en",
        "public_updated_at": "2020-11-30T16:33:00Z",
        "schema_name": "step_by_step_nav",
        "title": "Apply for a Short-term study visa: step by step",
        "web_url": "https://www.gov.uk/apply-short-term-study-visa",
        "withdrawn": false
      },
      {
        "api_path": "/api/content/apply-parent-child-student-visa",
        "api_url": "https://www.gov.uk/api/content/apply-parent-child-student-visa",
        "base_path": "/apply-parent-child-student-visa",
        "content_id": "a6bf2818-5035-45f7-ad38-c76cb8f1f251",
        "details": {
          "step_by_step_nav": {
            "steps": [
              {
                "contents": [
                  {
                    "text": "You might be eligible for different visas depending on why you're visiting the UK and how long for. ",
                    "type": "paragraph"
                  },
                  {
                    "contents": [
                      {
                        "href": "/check-uk-visa",
                        "text": "Check if you need a visa"
                      }
                    ],
                    "type": "list"
                  }
                ],
                "title": "Check if you need a visa"
              },
              {
                "contents": [
                  {
                    "contents": [
                      {
                        "href": "/parent-of-a-child-at-school-visa/eligibility",
                        "text": "Check what you need to show evidence of"
                      },
                      {
                        "href": "/parent-of-a-child-at-school-visa/documents-you-must-provide",
                        "text": "Check what documents you can use as evidence"
                      },
                      {
                        "href": "/tb-test-visa",
                        "text": "If your visa is for more than 6 months, check if you need a TB test"
                      }
                    ],
                    "type": "list"
                  }
                ],
                "title": "Prepare the evidence you need"
              },
              {
                "contents": [
                  {
                    "contents": [
                      {
                        "context": "£637",
                        "href": "/parent-of-a-child-at-school-visa/apply",
                        "text": "Apply for a visa and book an appointment"
                      },
                      {
                        "href": "/find-a-visa-application-centre",
                        "text": "Check where your visa appointment will be"
                      }
                    ],
                    "type": "list"
                  },
                  {
                    "text": "You should get a decision within 3 weeks of your appointment. ",
                    "type": "paragraph"
                  },
                  {
                    "text": "You might be able to pay an extra £500 for a decision within 5 working days or £1,000 for a decision within 24 hours (not including weekends or bank holidays). Check with your visa application centre.",
                    "type": "paragraph"
                  }
                ],
                "title": "Apply"
              },
              {
                "contents": [
                  {
                    "contents": [
                      {
                        "href": "/parent-of-a-child-at-school-visa/eligibility",
                        "text": "What you need to prove at your appointment"
                      }
                    ],
                    "type": "list"
                  },
                  {
                    "text": "You'll be told when a decision has been made about your visa.",
                    "type": "paragraph"
                  }
                ],
                "title": "Attend an appointment"
              },
              {
                "contents": [
                  {
                    "contents": [
                      {
                        "href": "/uk-border-control/at-border-control",
                        "text": "Check what you need to show at the UK border"
                      },
                      {
                        "href": "/uk-border-control",
                        "text": "Check what you can bring with you"
                      }
                    ],
                    "type": "list"
                  },
                  {
                    "text": "Keep the documents that prove why you're visiting the UK in your hand luggage so you can show them if asked. ",
                    "type": "paragraph"
                  },
                  {
                    "contents": [
                      {
                        "href": "/parent-of-a-child-at-school-visa/documents-you-must-provide",
                        "text": "Check the documents you can use to show why you're visiting the UK"
                      }
                    ],
                    "type": "list"
                  }
                ],
                "title": "Travel to the UK"
              },
              {
                "contents": [
                  {
                    "text": "If your visa allows you to stay in the UK for longer than 6 months, you'll need to collect your biometric residence permit soon after you arrive.",
                    "type": "paragraph"
                  },
                  {
                    "contents": [
                      {
                        "href": "/biometric-residence-permits/collect",
                        "text": "Collect your biometric residence permit"
                      }
                    ],
                    "type": "list"
                  },
                  {
                    "text": "Check your visa to find out when you must leave the UK. You may be able to extend your visa if you want to stay for longer.",
                    "type": "paragraph"
                  },
                  {
                    "contents": [
                      {
                        "href": "/parent-of-a-child-at-school-visa/extend-your-visa",
                        "text": "Extend your visa"
                      }
                    ],
                    "type": "list"
                  },
                  {
                    "text": "If you break the conditions of your visa you may not be able to return to the UK again.",
                    "type": "paragraph"
                  }
                ],
                "title": "After you arrive in the UK"
              }
            ],
            "title": "Apply for a Parent of a Child Student visa: step by step"
          }
        },
        "document_type": "step_by_step_nav",
        "links": {
          "pages_related_to_step_nav": [
            {
              "api_path": "/api/content/find-a-visa-application-centre",
              "api_url": "https://www.gov.uk/api/content/find-a-visa-application-centre",
              "base_path": "/find-a-visa-application-centre",
              "content_id": "aa055bd6-fde1-4471-8ac2-ac86241b4898",
              "document_type": "answer",
              "links": {
              },
              "locale": "en",
              "public_updated_at": "2014-11-24T17:50:24Z",
              "schema_name": "answer",
              "title": "Find a visa application centre",
              "web_url": "https://www.gov.uk/find-a-visa-application-centre",
              "withdrawn": false
            }
          ]
        },
        "locale": "en",
        "public_updated_at": "2023-09-27T14:59:48Z",
        "schema_name": "step_by_step_nav",
        "title": "Apply for a Parent of a Child Student visa: step by step",
        "web_url": "https://www.gov.uk/apply-parent-child-student-visa",
        "withdrawn": false
      }
    ],
    "suggested_ordered_related_items": [
      {
        "api_path": "/api/content/apply-to-come-to-the-uk",
        "api_url": "https://www.gov.uk/api/content/apply-to-come-to-the-uk",
        "base_path": "/apply-to-come-to-the-uk",
        "content_id": "76698ffe-70ab-4fda-be0d-755234f6d340",
        "document_type": "guide",
        "links": {
        },
        "locale": "en",
        "public_updated_at": "2019-06-20T13:46:12Z",
        "schema_name": "guide",
        "title": "How to apply for a visa to come to the UK",
        "web_url": "https://www.gov.uk/apply-to-come-to-the-uk",
        "withdrawn": false
      },
      {
        "api_path": "/api/content/check-uk-visa",
        "api_url": "https://www.gov.uk/api/content/check-uk-visa",
        "base_path": "/check-uk-visa",
        "content_id": "dc1a1744-4089-43b3-b2e3-4e397b6b15b1",
        "document_type": "smart_answer",
        "links": {
        },
        "locale": "en",
        "public_updated_at": "2021-06-16T08:18:46Z",
        "schema_name": "smart_answer",
        "title": "Check if you need a UK visa",
        "web_url": "https://www.gov.uk/check-uk-visa",
        "withdrawn": false
      },
      {
        "api_path": "/api/content/standard-visitor",
        "api_url": "https://www.gov.uk/api/content/standard-visitor",
        "base_path": "/standard-visitor",
        "content_id": "e1067450-7d13-45ff-ada4-5e3dd4025fb7",
        "document_type": "guide",
        "links": {
        },
        "locale": "en",
        "public_updated_at": "2015-04-24T09:54:26Z",
        "schema_name": "guide",
        "title": "Visit the UK as a Standard Visitor",
        "web_url": "https://www.gov.uk/standard-visitor",
        "withdrawn": false
      },
      {
        "api_path": "/api/content/contact-ukvi-inside-outside-uk",
        "api_url": "https://www.gov.uk/api/content/contact-ukvi-inside-outside-uk",
        "base_path": "/contact-ukvi-inside-outside-uk",
        "content_id": "c5d378e5-d800-4475-932f-d5e44615f91b",
        "document_type": "simple_smart_answer",
        "links": {
        },
        "locale": "en",
        "public_updated_at": "2017-06-02T15:53:45Z",
        "schema_name": "simple_smart_answer",
        "title": "Contact UK Visas and Immigration for help",
        "web_url": "https://www.gov.uk/contact-ukvi-inside-outside-uk",
        "withdrawn": false
      }
    ],
    "taxons": [
      {
        "api_path": "/api/content/entering-staying-uk/visa-application-centres",
        "api_url": "https://www.gov.uk/api/content/entering-staying-uk/visa-application-centres",
        "base_path": "/entering-staying-uk/visa-application-centres",
        "content_id": "d3df7728-db52-411f-afd2-44dbd09f553b",
        "description": "",
        "details": {
          "internal_name": "Visa application centres",
          "notes_for_editors": "",
          "visible_to_departmental_editors": false
        },
        "document_type": "taxon",
        "links": {
          "parent_taxons": [
            {
              "api_path": "/api/content/entering-staying-uk/visas-entry-clearance",
              "api_url": "https://www.gov.uk/api/content/entering-staying-uk/visas-entry-clearance",
              "base_path": "/entering-staying-uk/visas-entry-clearance",
              "content_id": "29480b00-dc4d-49a0-b48c-25dda8569325",
              "description": "",
              "details": {
                "internal_name": "Visas and entry clearance",
                "notes_for_editors": "",
                "visible_to_departmental_editors": false
              },
              "document_type": "taxon",
              "links": {
                "parent_taxons": [
                  {
                    "api_path": "/api/content/entering-staying-uk",
                    "api_url": "https://www.gov.uk/api/content/entering-staying-uk",
                    "base_path": "/entering-staying-uk",
                    "content_id": "ba3a9702-da22-487f-86c1-8334a730e559",
                    "details": {
                      "internal_name": "Entering and staying in the UK",
                      "notes_for_editors": "",
                      "visible_to_departmental_editors": true
                    },
                    "document_type": "taxon",
                    "links": {
                      "root_taxon": [
                        {
                          "api_path": "/api/content/",
                          "api_url": "https://www.gov.uk/api/content/",
                          "base_path": "/",
                          "content_id": "f3bbdec2-0e62-4520-a7fd-6ffd5d36e03a",
                          "document_type": "homepage",
                          "links": {
                          },
                          "locale": "en",
                          "public_updated_at": "2023-06-28T09:32:34Z",
                          "schema_name": "homepage",
                          "title": "GOV.UK homepage",
                          "web_url": "https://www.gov.uk/",
                          "withdrawn": false
                        }
                      ]
                    },
                    "locale": "en",
                    "phase": "live",
                    "public_updated_at": "2018-07-11T08:58:32Z",
                    "schema_name": "taxon",
                    "title": "Entering and staying in the UK",
                    "web_url": "https://www.gov.uk/entering-staying-uk",
                    "withdrawn": false
                  }
                ]
              },
              "locale": "en",
              "phase": "live",
              "public_updated_at": "2018-07-11T08:58:33Z",
              "schema_name": "taxon",
              "title": "Visas and entry clearance",
              "web_url": "https://www.gov.uk/entering-staying-uk/visas-entry-clearance",
              "withdrawn": false
            }
          ]
        },
        "locale": "en",
        "phase": "live",
        "public_updated_at": "2018-07-11T08:58:33Z",
        "schema_name": "taxon",
        "title": "Visa application centres",
        "web_url": "https://www.gov.uk/entering-staying-uk/visa-application-centres",
        "withdrawn": false
      }
    ]
  },
  "locale": "en",
  "phase": "live",
  "public_updated_at": "2014-11-24T17:50:24Z",
  "publishing_app": "publisher",
  "publishing_request_id": "21-1708096537.293-10.13.21.112-30719",
  "publishing_scheduled_at": null,
  "rendering_app": "government-frontend",
  "scheduled_publishing_delay_seconds": null,
  "schema_name": "answer",
  "title": "Find a visa application centre",
  "updated_at": "2024-02-16T15:15:39Z",
  "withdrawn_notice": {
  }
}